agmap.py
agmap-0.0.1.dist-info/METADATA
agmap-0.0.1.dist-info/WHEEL
agmap-0.0.1.dist-info/top_level.txt
agmap-0.0.1.dist-info/RECORD
