Metadata-Version: 2.1
Name: agmap
Version: 0.0.1
Summary: Audible ASIN to goodreads mapping 
Author: Gautam Datla
Classifier: Programming Language :: Python :: 3
Classifier: License :: OSI Approved :: MIT License
Classifier: Operating System :: OS Independent
Requires-Python: >=3.6
